tm_easy/__init__.py
tm_easy/tm_easy.py
tm_easy-0.0.25.dist-info/LICENSE
tm_easy-0.0.25.dist-info/METADATA
tm_easy-0.0.25.dist-info/WHEEL
tm_easy-0.0.25.dist-info/top_level.txt
tm_easy-0.0.25.dist-info/RECORD
